{"questins":["Мощность больше 200?","Внедорожник?","Грузовик?","Отечественный?","Черный цвет?","V-образный двигатель?","Обьем двигателя больше 2.7L?","Дороже 2 млн?","Американский бренд?","Азиатский бренд?","Красный цвет?"],
		"hypothesis":[{"statrWith":0.05,"name":"Ford Focus","hypothesiss":[{"ifTrue":0.05,"ifFalse":0.453634085},{"ifTrue":0.05,"ifFalse":0.295739348},{"ifTrue":0.05,"ifFalse":0.273182957},{"ifTrue":0.05,"ifFalse":0.273182957},{"ifTrue":0.05,"ifFalse":0.318295739},{"ifTrue":0.05,"ifFalse":0.363408521},{"ifTrue":0.05,"ifFalse":0.498746867},{"ifTrue":0.05,"ifFalse":0.363408521},{"ifTrue":0.95,"ifFalse":0.238845144},{"ifTrue":0.05,"ifFalse":0.273182957},{"ifTrue":0.05,"ifFalse":0.318295739}]},{"statrWith":0.05,"name":"Toyota Land Cruiser Prado","hypothesiss":[{"ifTrue":0.95,"ifFalse":0.427821522},{"ifTrue":0.95,"ifFalse":0.262467192},{"ifTrue":0.05,"ifFalse":0.273182957},{"ifTrue":0.05,"ifFalse":0.273182957},{"ifTrue":0.95,"ifFalse":0.286089239},{"ifTrue":0.95,"ifFalse":0.333333333},{"ifTrue":0.95,"ifFalse":0.475065617},{"ifTrue":0.95,"ifFalse":0.333333333},{"ifTrue":0.05,"ifFalse":0.273182957},{"ifTrue":0.95,"ifFalse":0.238845144},{"ifTrue":0.05,"ifFalse":0.318295739}]},{"statrWith":0.05,"name":"Hyundai Solaris","hypothesiss":[{"ifTrue":0.05,"ifFalse":0.453634085},{"ifTrue":0.05,"ifFalse":0.295739348},{"ifTrue":0.05,"ifFalse":0.273182957},{"ifTrue":0.05,"ifFalse":0.273182957},{"ifTrue":0.95,"ifFalse":0.286089239},{"ifTrue":0.05,"ifFalse":0.363408521},{"ifTrue":0.05,"ifFalse":0.498746867},{"ifTrue":0.05,"ifFalse":0.363408521},{"ifTrue":0.05,"ifFalse":0.273182957},{"ifTrue":0.95,"ifFalse":0.238845144},{"ifTrue":0.05,"ifFalse":0.318295739}]},{"statrWith":0.05,"name":"Renault Sandero Stepway","hypothesiss":[{"ifTrue":0.05,"ifFalse":0.453634085},{"ifTrue":0.5,"ifFalse":0.279487179},{"ifTrue":0.05,"ifFalse":0.273182957},{"ifTrue":0.05,"ifFalse":0.273182957},{"ifTrue":0.95,"ifFalse":0.286089239},{"ifTrue":0.05,"ifFalse":0.363408521},{"ifTrue":0.05,"ifFalse":0.498746867},{"ifTrue":0.05,"ifFalse":0.363408521},{"ifTrue":0.05,"ifFalse":0.273182957},{"ifTrue":0.05,"ifFalse":0.273182957},{"ifTrue":0.05,"ifFalse":0.318295739}]},{"statrWith":0.05,"name":"Freightliner","hypothesiss":[{"ifTrue":0.95,"ifFalse":0.427821522},{"ifTrue":0.05,"ifFalse":0.295739348},{"ifTrue":0.95,"ifFalse":0.238845144},{"ifTrue":0.05,"ifFalse":0.273182957},{"ifTrue":0.05,"ifFalse":0.318295739},{"ifTrue":0.05,"ifFalse":0.363408521},{"ifTrue":0.95,"ifFalse":0.475065617},{"ifTrue":0.05,"ifFalse":0.363408521},{"ifTrue":0.95,"ifFalse":0.238845144},{"ifTrue":0.05,"ifFalse":0.273182957},{"ifTrue":0.95,"ifFalse":0.286089239}]},{"statrWith":0.05,"name":"Tesla Model S","hypothesiss":[{"ifTrue":0.95,"ifFalse":0.427821522},{"ifTrue":0.05,"ifFalse":0.295739348},{"ifTrue":0.05,"ifFalse":0.273182957},{"ifTrue":0.05,"ifFalse":0.273182957},{"ifTrue":0.05,"ifFalse":0.318295739},{"ifTrue":0.05,"ifFalse":0.363408521},{"ifTrue":0.05,"ifFalse":0.498746867},{"ifTrue":0.95,"ifFalse":0.333333333},{"ifTrue":0.95,"ifFalse":0.238845144},{"ifTrue":0.05,"ifFalse":0.273182957},{"ifTrue":0.95,"ifFalse":0.286089239}]},{"statrWith":0.05,"name":"Suzuki Grand Vitara","hypothesiss":[{"ifTrue":0.05,"ifFalse":0.453634085},{"ifTrue":0.95,"ifFalse":0.262467192},{"ifTrue":0.05,"ifFalse":0.273182957},{"ifTrue":0.05,"ifFalse":0.273182957},{"ifTrue":0.05,"ifFalse":0.318295739},{"ifTrue":0.05,"ifFalse":0.363408521},{"ifTrue":0.05,"ifFalse":0.498746867},{"ifTrue":0.05,"ifFalse":0.363408521},{"ifTrue":0.05,"ifFalse":0.273182957},{"ifTrue":0.95,"ifFalse":0.238845144},{"ifTrue":0.05,"ifFalse":0.318295739}]},{"statrWith":0.05,"name":"Fiat Ducato","hypothesiss":[{"ifTrue":0.05,"ifFalse":0.453634085},{"ifTrue":0.05,"ifFalse":0.295739348},{"ifTrue":0.95,"ifFalse":0.238845144},{"ifTrue":0.05,"ifFalse":0.273182957},{"ifTrue":0.05,"ifFalse":0.318295739},{"ifTrue":0.05,"ifFalse":0.363408521},{"ifTrue":0.05,"ifFalse":0.498746867},{"ifTrue":0.05,"ifFalse":0.363408521},{"ifTrue":0.05,"ifFalse":0.273182957},{"ifTrue":0.05,"ifFalse":0.273182957},{"ifTrue":0.05,"ifFalse":0.318295739}]},{"statrWith":0.05,"name":"Isuzu Elf","hypothesiss":[{"ifTrue":0.05,"ifFalse":0.453634085},{"ifTrue":0.05,"ifFalse":0.295739348},{"ifTrue":0.95,"ifFalse":0.238845144},{"ifTrue":0.05,"ifFalse":0.273182957},{"ifTrue":0.05,"ifFalse":0.318295739},{"ifTrue":0.05,"ifFalse":0.363408521},{"ifTrue":0.95,"ifFalse":0.475065617},{"ifTrue":0.05,"ifFalse":0.363408521},{"ifTrue":0.05,"ifFalse":0.273182957},{"ifTrue":0.95,"ifFalse":0.238845144},{"ifTrue":0.05,"ifFalse":0.318295739}]},{"statrWith":0.05,"name":"Nissan GT-R","hypothesiss":[{"ifTrue":0.95,"ifFalse":0.427821522},{"ifTrue":0.05,"ifFalse":0.295739348},{"ifTrue":0.05,"ifFalse":0.273182957},{"ifTrue":0.05,"ifFalse":0.273182957},{"ifTrue":0.05,"ifFalse":0.318295739},{"ifTrue":0.95,"ifFalse":0.333333333},{"ifTrue":0.95,"ifFalse":0.475065617},{"ifTrue":0.95,"ifFalse":0.333333333},{"ifTrue":0.05,"ifFalse":0.273182957},{"ifTrue":0.95,"ifFalse":0.238845144},{"ifTrue":0.05,"ifFalse":0.318295739}]},{"statrWith":0.05,"name":"Mercedes G500","hypothesiss":[{"ifTrue":0.95,"ifFalse":0.427821522},{"ifTrue":0.95,"ifFalse":0.262467192},{"ifTrue":0.05,"ifFalse":0.273182957},{"ifTrue":0.05,"ifFalse":0.273182957},{"ifTrue":0.95,"ifFalse":0.286089239},{"ifTrue":0.95,"ifFalse":0.333333333},{"ifTrue":0.95,"ifFalse":0.475065617},{"ifTrue":0.95,"ifFalse":0.333333333},{"ifTrue":0.05,"ifFalse":0.273182957},{"ifTrue":0.05,"ifFalse":0.273182957},{"ifTrue":0.95,"ifFalse":0.286089239}]},{"statrWith":0.05,"name":"Dodge Charger","hypothesiss":[{"ifTrue":0.95,"ifFalse":0.427821522},{"ifTrue":0.05,"ifFalse":0.295739348},{"ifTrue":0.05,"ifFalse":0.273182957},{"ifTrue":0.05,"ifFalse":0.273182957},{"ifTrue":0.95,"ifFalse":0.286089239},{"ifTrue":0.95,"ifFalse":0.333333333},{"ifTrue":0.95,"ifFalse":0.475065617},{"ifTrue":0.95,"ifFalse":0.333333333},{"ifTrue":0.95,"ifFalse":0.238845144},{"ifTrue":0.05,"ifFalse":0.273182957},{"ifTrue":0.05,"ifFalse":0.318295739}]},{"statrWith":0.05,"name":"Audi Q3","hypothesiss":[{"ifTrue":0.05,"ifFalse":0.453634085},{"ifTrue":0.05,"ifFalse":0.295739348},{"ifTrue":0.05,"ifFalse":0.273182957},{"ifTrue":0.05,"ifFalse":0.273182957},{"ifTrue":0.05,"ifFalse":0.318295739},{"ifTrue":0.05,"ifFalse":0.363408521},{"ifTrue":0.05,"ifFalse":0.498746867},{"ifTrue":0.05,"ifFalse":0.363408521},{"ifTrue":0.05,"ifFalse":0.273182957},{"ifTrue":0.05,"ifFalse":0.273182957},{"ifTrue":0.05,"ifFalse":0.318295739}]},{"statrWith":0.05,"name":"ВАЗ 2115","hypothesiss":[{"ifTrue":0.05,"ifFalse":0.453634085},{"ifTrue":0.05,"ifFalse":0.295739348},{"ifTrue":0.05,"ifFalse":0.273182957},{"ifTrue":0.95,"ifFalse":0.238845144},{"ifTrue":0.05,"ifFalse":0.318295739},{"ifTrue":0.05,"ifFalse":0.363408521},{"ifTrue":0.05,"ifFalse":0.498746867},{"ifTrue":0.05,"ifFalse":0.363408521},{"ifTrue":0.05,"ifFalse":0.273182957},{"ifTrue":0.05,"ifFalse":0.273182957},{"ifTrue":0.05,"ifFalse":0.318295739}]},{"statrWith":0.05,"name":"ГАЗель NEXT","hypothesiss":[{"ifTrue":0.05,"ifFalse":0.453634085},{"ifTrue":0.05,"ifFalse":0.295739348},{"ifTrue":0.95,"ifFalse":0.238845144},{"ifTrue":0.95,"ifFalse":0.238845144},{"ifTrue":0.05,"ifFalse":0.318295739},{"ifTrue":0.05,"ifFalse":0.363408521},{"ifTrue":0.95,"ifFalse":0.475065617},{"ifTrue":0.05,"ifFalse":0.363408521},{"ifTrue":0.05,"ifFalse":0.273182957},{"ifTrue":0.05,"ifFalse":0.273182957},{"ifTrue":0.05,"ifFalse":0.318295739}]},{"statrWith":0.05,"name":"УАЗ Патриот","hypothesiss":[{"ifTrue":0.05,"ifFalse":0.453634085},{"ifTrue":0.95,"ifFalse":0.262467192},{"ifTrue":0.05,"ifFalse":0.273182957},{"ifTrue":0.95,"ifFalse":0.238845144},{"ifTrue":0.05,"ifFalse":0.318295739},{"ifTrue":0.05,"ifFalse":0.363408521},{"ifTrue":0.05,"ifFalse":0.498746867},{"ifTrue":0.05,"ifFalse":0.363408521},{"ifTrue":0.05,"ifFalse":0.273182957},{"ifTrue":0.05,"ifFalse":0.273182957},{"ifTrue":0.95,"ifFalse":0.318295739}]},{"statrWith":0.05,"name":"Lamborghini Aventador","hypothesiss":[{"ifTrue":0.95,"ifFalse":0.427821522},{"ifTrue":0.05,"ifFalse":0.295739348},{"ifTrue":0.05,"ifFalse":0.273182957},{"ifTrue":0.05,"ifFalse":0.273182957},{"ifTrue":0.05,"ifFalse":0.318295739},{"ifTrue":0.95,"ifFalse":0.333333333},{"ifTrue":0.95,"ifFalse":0.475065617},{"ifTrue":0.95,"ifFalse":0.333333333},{"ifTrue":0.05,"ifFalse":0.273182957},{"ifTrue":0.05,"ifFalse":0.273182957},{"ifTrue":0.05,"ifFalse":0.318295739}]},{"statrWith":0.05,"name":"ГАЗ Чайка","hypothesiss":[{"ifTrue":0.95,"ifFalse":0.427821522},{"ifTrue":0.05,"ifFalse":0.295739348},{"ifTrue":0.05,"ifFalse":0.273182957},{"ifTrue":0.95,"ifFalse":0.238845144},{"ifTrue":0.95,"ifFalse":0.286089239},{"ifTrue":0.95,"ifFalse":0.333333333},{"ifTrue":0.95,"ifFalse":0.475065617},{"ifTrue":0.05,"ifFalse":0.363408521},{"ifTrue":0.05,"ifFalse":0.273182957},{"ifTrue":0.05,"ifFalse":0.273182957},{"ifTrue":0.05,"ifFalse":0.318295739}]},{"statrWith":0.05,"name":"Jeep Wrangler","hypothesiss":[{"ifTrue":0.95,"ifFalse":0.427821522},{"ifTrue":0.95,"ifFalse":0.262467192},{"ifTrue":0.05,"ifFalse":0.273182957},{"ifTrue":0.05,"ifFalse":0.273182957},{"ifTrue":0.95,"ifFalse":0.318295739},{"ifTrue":0.05,"ifFalse":0.363408521},{"ifTrue":0.05,"ifFalse":0.498746867},{"ifTrue":0.95,"ifFalse":0.333333333},{"ifTrue":0.95,"ifFalse":0.238845144},{"ifTrue":0.05,"ifFalse":0.273182957},{"ifTrue":0.05,"ifFalse":0.286089239}]},{"statrWith":0.05,"name":"ЗИЛ 130","hypothesiss":[{"ifTrue":0.05,"ifFalse":0.453634085},{"ifTrue":0.05,"ifFalse":0.295739348},{"ifTrue":0.95,"ifFalse":0.238845144},{"ifTrue":0.95,"ifFalse":0.238845144},{"ifTrue":0.95,"ifFalse":0.318295739},{"ifTrue":0.95,"ifFalse":0.333333333},{"ifTrue":0.95,"ifFalse":0.475065617},{"ifTrue":0.05,"ifFalse":0.363408521},{"ifTrue":0.05,"ifFalse":0.273182957},{"ifTrue":0.05,"ifFalse":0.273182957},{"ifTrue":0.05,"ifFalse":0.318295739}]}]}